aispm/__init__.py
aispm/main.py
aispm-0.0.0.dist-info/METADATA
aispm-0.0.0.dist-info/WHEEL
aispm-0.0.0.dist-info/top_level.txt
aispm-0.0.0.dist-info/RECORD
