Metadata-Version: 2.1
Name: aispm
Version: 0.0.0
Summary: aispm
Author-email: James <test@example.com>
Classifier: Programming Language :: Python :: 3
Classifier: Operating System :: OS Independent
Requires-Python: >=3.11
